dsnet/__init__.py
dsnet/core.py
dsnet/crypto.py
dsnet/logger.py
dsnet/message.py
dsnet/token.py
test/__init__.py
test/test_core.py
test/test_token.py
datashare_network_core-0.13.0.dist-info/LICENSE.txt
datashare_network_core-0.13.0.dist-info/METADATA
datashare_network_core-0.13.0.dist-info/WHEEL
datashare_network_core-0.13.0.dist-info/top_level.txt
datashare_network_core-0.13.0.dist-info/RECORD
