Metadata-Version: 2.1
Name: datashare-network-core
Version: 0.13.0
Summary: Core Datashare Network Library
Home-page: https://github.com/icij/datashare-network-lib
License: UNKNOWN
Keywords: datashare,api,network,cryptography
Platform: UNKNOWN
Classifier: Programming Language :: Python :: 3
Classifier: Programming Language :: Python :: 3.7
Classifier: Programming Language :: Python :: 3.8
Classifier: Intended Audience :: Developers
Classifier: License :: OSI Approved :: GNU Affero General Public License v3
Classifier: Operating System :: OS Independent
Classifier: Topic :: Security :: Cryptography
Requires-Python: >=3.7
License-File: LICENSE.txt
Requires-Dist: cryptography (>=3.0)
Requires-Dist: sscred (==0.2.1)
